pyxpcsviewer/__init__.py
pyxpcsviewer/cli.py
pyxpcsviewer/default_setting.py
pyxpcsviewer/file_locator.py
pyxpcsviewer/icons_rc.py
pyxpcsviewer/viewer_kernel.py
pyxpcsviewer/viewer_ui.py
pyxpcsviewer/web_gui.py
pyxpcsviewer/xpcs_file.py
pyxpcsviewer/xpcs_viewer.py
pyxpcsviewer/configure/aps_8idi.json
pyxpcsviewer/fileIO/__init__.py
pyxpcsviewer/fileIO/aps_8idi.py
pyxpcsviewer/fileIO/ftype_utils.py
pyxpcsviewer/fileIO/hdf_reader.py
pyxpcsviewer/fileIO/qmap_utils.py
pyxpcsviewer/helper/__init__.py
pyxpcsviewer/helper/fitting.py
pyxpcsviewer/helper/listmodel.py
pyxpcsviewer/module/__init__.py
pyxpcsviewer/module/average_toolbox.py
pyxpcsviewer/module/g2mod.py
pyxpcsviewer/module/intt.py
pyxpcsviewer/module/saxs1d.py
pyxpcsviewer/module/saxs2d.py
pyxpcsviewer/module/stability.py
pyxpcsviewer/module/tauq.py
pyxpcsviewer/module/twotime.py
pyxpcsviewer/module/twotime_utils.py
pyxpcsviewer/module_web/saxs1d.py
pyxpcsviewer/plothandler/__init__.py
pyxpcsviewer/plothandler/matplot_qt.py
pyxpcsviewer/plothandler/pyqtgraph_handler.py
pyxpcsviewer/ui/xpcs.ui
pyxpcsviewer/ui/resources/icons.qrc
pyxpcsviewer/ui/resources/icons8-giraffe-full-body-100.png
xpcs_viewer-1.0.6.dist-info/licenses/LICENSE
xpcs_viewer-1.0.6.dist-info/METADATA
xpcs_viewer-1.0.6.dist-info/WHEEL
xpcs_viewer-1.0.6.dist-info/entry_points.txt
xpcs_viewer-1.0.6.dist-info/top_level.txt
xpcs_viewer-1.0.6.dist-info/RECORD
