Metadata-Version: 2.4
Name: xpcs-viewer
Version: 1.0.6
Summary: pyXPCSViewer: A python-based interactive tool to visualize and model XPCS dataset
Author-email: Miaoqi Chu <mqichu@anl.gov>
Maintainer-email: Miaoqi Chu <mqichu@anl.gov>
License: MIT
Project-URL: bugs, https://github.com/AZjk/pyxpcsviewer/issues
Project-URL: changelog, https://github.com/AZjk/pyxpcsviewer/blob/master/changelog.md
Project-URL: homepage, https://github.com/AZjk/pyxpcsviewer
Keywords: XPCS,X-ray,photon correlation spectroscopy,synchrotron,visualization,science
Classifier: Development Status :: 4 - Beta
Classifier: Intended Audience :: Science/Research
Classifier: Intended Audience :: Developers
Classifier: Topic :: Scientific/Engineering
Classifier: Topic :: Scientific/Engineering :: Physics
Classifier: Topic :: Scientific/Engineering :: Visualization
Classifier: Topic :: Software Development :: Libraries :: Python Modules
Classifier: License :: OSI Approved :: MIT License
Classifier: Programming Language :: Python
Classifier: Programming Language :: Python :: 3.10
Classifier: Programming Language :: Python :: 3.11
Classifier: Programming Language :: Python :: 3.12
Classifier: Operating System :: OS Independent
Classifier: Natural Language :: English
License-File: LICENSE
Requires-Dist: numpy
Requires-Dist: scipy
Requires-Dist: h5py
Requires-Dist: matplotlib
Requires-Dist: pyqtgraph
Requires-Dist: pandas
Requires-Dist: scikit-learn
Requires-Dist: joblib
Requires-Dist: tqdm
Requires-Dist: hdf5plugin
Requires-Dist: pyside6==6.8.3
Provides-Extra: dev
Requires-Dist: coverage; extra == "dev"
Requires-Dist: pytest; extra == "dev"
Requires-Dist: pytest-cov; extra == "dev"
Requires-Dist: mypy; extra == "dev"
Requires-Dist: ruff; extra == "dev"
Provides-Extra: docs
Requires-Dist: sphinx; extra == "docs"
Requires-Dist: sphinx-rtd-theme; extra == "docs"
Dynamic: license-file
